README.md
batchdist/__init__.py
batchdist/examples/external/sinkhorn_layer.py
batchdist/examples/simple_example.py
batchdist/examples/sinkhorn_example.py
batchdist/src/batch_distance.py
batchdist-0.1.3.dist-info/WHEEL
batchdist-0.1.3.dist-info/METADATA
batchdist-0.1.3.dist-info/RECORD
