Metadata-Version: 2.1
Name: batchdist
Version: 0.1.3
Summary: A small pytorch package for efficiently running pair-wise operations such as distances on the batch-level.
Home-page: https://github.com/mi92/batchdist
License: BSD-3-Clause
Author: Michael Moor
Author-email: michael.moor@bsse.ethz.ch
Requires-Python: >=3.7,<4.0
Classifier: License :: OSI Approved :: BSD License
Classifier: Programming Language :: Python :: 3
Classifier: Programming Language :: Python :: 3.7
Classifier: Programming Language :: Python :: 3.8
Classifier: Programming Language :: Python :: 3.9
Requires-Dist: torch (>=1.6.0,<2.0.0)
Project-URL: Repository, https://github.com/mi92/batchdist
